{
  "projectId": "gen-lang-client-0953954735",
  "appId": "1:1063857725907:web:4b02083c254cb947cd0f26",
  "apiKey": "AIzaSyDdR7hU-XCrMDqwtj-rUntbszLpQIjPMk0",
  "authDomain": "gen-lang-client-0953954735.firebaseapp.com",
  "firestoreDatabaseId": "ai-studio-genfocus-4421d6d5-bcda-4688-86d7-92ea1e9faec9",
  "storageBucket": "gen-lang-client-0953954735.firebasestorage.app",
  "messagingSenderId": "1063857725907",
  "measurementId": "",
  "oAuthClientId": "1063857725907-7t5sq94ucl7l1n1e38uusbj2h0fhejlm.apps.googleusercontent.com"
}